test_x_package/__init__.py
test_x_package-0.1.6.dist-info/METADATA
test_x_package-0.1.6.dist-info/WHEEL
test_x_package-0.1.6.dist-info/top_level.txt
test_x_package-0.1.6.dist-info/RECORD
