Metadata-Version: 2.4
Name: test-x-package
Version: 0.1.6
Summary: Just a test package to develop ci jobs
Requires-Python: >=3.12
